{
    "\"ce moment où\"": "2021-05-10",
    "casse-toi pauvre": "2021-05-10",
    "\"deuxième effet\"": "2021-05-10",
    "question répondue": "2021-05-10",
    "\"traverse la rue\"": "2021-05-10",
    "\"vous entendra crier\"": "2021-05-10",
    "\"travailler plus\"": "2021-05-10",
    "\"il faut choisir\"": "",
    "\"damnés de la terre\"": "",
    "\"tu pousses le bouchon\"": "",
    "\"toute la misère du monde\"": "",
    "breaking": "",
    "\"à la vie, à\"": "",
    "\"vers l'infini et\"": "",
    "\"Hasta la vista\"": "",
    "\"m’a tuer\"": "",
    "\"est le nouveau\"": "",
    "\"is the new\"": "",
    "\"Liberté, égalité\"": "",
    "\"c'est mourir un peu\"": "",
    "\"Yes we\"": "",
    "\"make the planet\" again": "",
    "\"manger chinois ou\"": "",
    "\"est-ce que tu\"": "",
    "cadeau infini": "",
    "numéro 1 santé ligne": "",
    "renseignement simplement": "",
    "source réussite": "",
    "mérite \"parce qu'on le\"": "",
    "numéro numéro \"de tous les\"": "",
    "bien renseignement \"plus que des\"": "",
    "numéro 1 aider": "",
    "118 712 répondre vite bien": "",
    "chaîne action suspense": "",
    "chiffre bière": "",
    "français évidemment": "",
    "chocolat noir griffe": "",
    "information droit": "",
    "20 minute second": "",
    "2 m rassemble": "",
    "ici brasser \"que ça se\"": "",
    "patinoire patinoire \"et toute la\"": "",
    "centre monde bouger": "",
    "prendre avance": "",
    "textile expert": "",
    "laver vivre": "",
    "sens client": "",
    "oh thank heaven for 7-eleven": "",
    "cœur vie": "",
    "makes beef sing": "",
    "vie auchan": "",
    "cool tv": "",
    "chaîne absolument 1dispensabl": "",
    "télé vrai": "",
    "indispensable investir bourse": "",
    "passionner livre": "",
    "panier salade \"près de chez vous\"": "",
    "build your singularity": "",
    "plaisir sécurité": "",
    "leader européen fabricant abri piscine": "",
    "abri avance": "",
    "croire potentiel enfant": "",
    "croire potentiel": "",
    "pouvoir apprendre": "",
    "réussir \"ils ont tout pour\"": "",
    "high performance delivered": "",
    "empowering people": "",
    "explor beyond limits": "",
    "internet service immobilier": "",
    "santé travail": "",
    "opération anti-rhum": "",
    "vie continue rhume": "",
    "aider défense naturel": "",
    "actimel renforcer défense naturel": "",
    "complet surprenant prix étonnant": "",
    "petit prix grand sourire": "",
    "grand héros \"de tous les\"": "",
    "where you' r the center of the action": "",
    "actif intérieur voir extérieur \"et ça se\"": "",
    "sensation unique": "",
    "concevoir impressionner": "",
    "see what could be": "",
    "pouvoir rouler cher": "",
    "roule cher": "",
    "initiateur plaisir": "",
    "better work better life": "",
    "travailler heureux vivre mieux": "",
    "communiquer simplement": "",
    "impossible is nothing": "",
    "forever sport": "",
    "victoire \"est en nous\"": "",
    "y gagner": "",
    "celebrate originality": "",
    "communiquer adresse": "",
    "bridging science with life": "",
    "pompe funèbre simplifier vie": "",
    "real life drama": "",
    "perfekt in form und funktion": "",
    "passion transporte": "",
    "lire écrire voyager": "",
    "bière initié 1074": "",
    "monde différence": "",
    "your agriculture company": "",
    "organisateur transport": "",
    "contraire monde \"de seul au\"": "",
    "prendre main demain": "",
    "faire -vou travail": "",
    "engager jusque bout": "",
    "the strength to be there": "",
    "rapprocher culture": "",
    "belong anywhere": "",
    "aller loin": "",
    "monde attendre": "",
    "soleil ligne \"sur toute la\"": "",
    "haut couleur": "",
    "spécialiste corse": "",
    " \"tellement proche de vous\"": "",
    "faire ciel bel endroit terre": "",
    "gagner coeur monde": "",
    "france is in the air": "",
    "out of control": "",
    "air vie": "",
    "voyage bien davantage": "",
    "haut fort": "",
    "monde vacance": "",
    "mâchez respirer": "",
    "parfum changer vie": "",
    "bon maison \"d'être à la\"": "",
    "y chose air wick": "",
    "mettre défi": "",
    "pied \"c'est le\"": "",
    "fou afflelou fou": "",
    "dommage opticien \"qu'il ne soit qu'\"": "",
    "déménager confiant": "",
    "assurance santé garantir mal tête": "",
    "demander nous": "",
    "it means great deal": "",
    "architect of an internet world": "",
    "faire progresser génération": "",
    "aluminium échelle humain": "",
    "ventilation alder": "",
    "meilleur qualité meilleur prix": "",
    "place nouveau consommateur": "",
    "pur performance": "",
    "cœur sportif": "",
    "technologie gagne": "",
    "vie trop court conduire italien \"pour ne pas\"": "",
    "cœur être machine": "",
    "meccanica dell emozioni": "",
    "beau secret": "",
    "global trade starts here": "",
    "alice clair": "",
    "libre idée \"d'avoir des\"": "",
    "afficher couleur": "",
    "passionner nature": "",
    "geste bien-être intérieur": "",
    "santé \"toujours plus proche\"": "",
    "z. \"avec vous de a à\"": "",
    "restez simple spectateur": "",
    "is all you need": "",
    "être bon main": "",
    "île soleil": "",
    "pays pâte": "",
    "enjoy pler power": "",
    "jour fête alsa \"c'est tous les\"": "",
    "dessert être fier": "",
    "hacemos viaj má fácil": "",
    "alsacez vous": "",
    "façonner avenir": "",
    "designing fluidity": "",
    "intelligence provisoire": "",
    "playground for innovation": "",
    "haver happy period": "",
    "passer bon semaine": "",
    "assurance \"c'était comment l'\"": "",
    "and you' r done": "",
    "trouver bonheur": "",
    "the futur is fusion": "",
    "enabling today": "",
    "centre beauté auto": "",
    "realize the potential": "",
    "décorateur extérieur": "",
    "amour goût": "",
    "amour goût vrai": "",
    "prendre sens": "",
    "donner vie \"du son à la\"": "",
    "écoute nouveau génération": "",
    "assurance gagner": "",
    "enjoy the journey": "",
    "raise glass to planet earth": "",
    "pays pyrénée": "",
    "soulier mode 1900": "",
    "chausseur savoir chausser": "",
    "ca fort fruit": "",
    "force fruit": "",
    "animal vivre aimer": "",
    "premier magazine animation manga": "",
    "site bouger rêve": "",
    "professionnel désinfection": "",
    "style ville": "",
    "numéro 1 emploi ligne": "",
    "believe it": "",
    "calcaire affaire \"c'est son\"": "",
    "souffle avance": "",
    "better answers faster": "",
    "inviter grand jambon table": "",
    "irrésistible tentation": "",
    "peau tranquille": "",
    "prendre rendez-vous avenir": "",
    "apéricube déclare apéritif": "",
    "vivre différence": "",
    "assurance gagner santé \"qui me fait\"": "",
    "goût pureté": "",
    "three in one protection for your family": "",
    "gets teeth white keep teeth white": "",
    "cœur piscine qualité": "",
    "monde salle bain": "",
    "objectif réussite": "",
    "art divertir": "",
    "placard \"les as du\"": "",
    "entertainment your way": "",
    "énergie sens propre": "",
    "don' t shop for it argo it": "",
    "cœur automobile": "",
    "ariel merveille": "",
    "aller faire merveille": "",
    "santé naturellement": "",
    "faciliter vous vie": "",
    "vivre curieux": "",
    "ouverture permanent": "",
    "aimer déjà": "",
    "serving your inspiration": "",
    "art unique": "",
    "déménager stress": "",
    "efficace aimable prix raisonnable": "",
    "vie facile": "",
    "premier entreprise france": "",
    "entreprise france": "",
    "art manière": "",
    "we care about car we care about you": "",
    "bulle plein vie réussir": "",
    "why pay more": "",
    "saving you money every day": "",
    "the world is your address": "",
    "jamais finir service \"on n'a\" \"de vous rendre\"": "",
    "men saner in corpore san": "",
    "anima sana in corpore sano": "",
    "sound mind sound body": "",
    "want it more": "",
    "sens technologique": "",
    "am electric": "",
    "y frotte y pique": "",
    "leader pharmacie 1999": "",
    "vraiment \"ouvert à tous\"": "",
    "professionnel assurer": "",
    "numérique source": "",
    "demander nous avenir": "",
    "avenir \"est à moi\"": "",
    "rock solid heart touching": "",
    "inspiring innovation persister perfection": "",
    "rechercher exceptionnel": "",
    "in search of incredible": "",
    "innovation makes difference": "",
    "multimétier métier \"c'est notre\"": "",
    "meilleur performance": "",
    "vie sport": "",
    "getting you there": "",
    "your world delivered": "",
    "mobilizing your world": "",
    "your business technologists powering progress": "",
    "seeing thing differently": "",
    "vision conseil": "",
    "célibataire exigeant": "",
    "art aimer": "",
    "anticiper innovation": "",
    "bienvenue monde": "",
    "tendrement expert": "",
    "plaisir parent": "",
    "vie vrai": "",
    "vie auchan changer vie": "",
    "vivre mieux vivre cher": "",
    "vie aimer \"et vous la\"": "",
    "vie chang": "",
    "cher temps": "",
    "vie ville": "",
    "téléphoner devenir hyper cher": "",
    "technique passion": "",
    "truth in engineering": "",
    "avance technologie": "",
    "vorsprung durch technik": "",
    "bien entendre": "",
    "écouter livre \"c'est un\"": "",
    "avenir féminin": "",
    "journal falloir \"qu'il vous\"": "",
    "come walkabout": "",
    "australie nul part ailleurs": "",
    "the charming way to fly": "",
    "assurance bien voyager": "",
    "feeling good the move": "",
    "plaisir automobile": "",
    "premier journal mettre place conducteur": "",
    "louer mieux louez bleu": "",
    "radio compagnon route \"plus qu'une\"": "",
    "the power of we": "",
    "be free": "",
    "beal résultat naturel": "",
    "partout vie goût": "",
    "uni solidaire": "",
    "gusto pieno della vita": "",
    "aile humanitaire": "",
    "we try harder": "",
    "mobilité cler main": "",
    "penser loin": "",
    "all american food": "",
    "vivre confier": "",
    "avoir chose vivre": "",
    "réinventer métier": "",
    "know you can": "",
    "mettre \"plus t'en\" \"plus t'en as\"": "",
    "the shape of broadcasting to come": "",
    "engagement service rendre": "",
    "partenaire maison": "",
    "exigeant exigeant": "",
    "redécouvrir apprentissage langue": "",
    "prix fou": "",
    "bon plan prix fou": "",
    "360 degré bonheur": "",
    "petit fromage grand sourire": "",
    "idée embellir": "",
    "bel vite": "",
    "new is old": "",
    "on envisager repas badoit": "",
    "reprendre bien légèreté \"un peu de\"": "",
    "arrêter manger merde": "",
    "plaisir pain": "",
    "bon appétit bon baguépi": "",
    "y vie baguépi \"a de la\"": "",
    "sel grand espace": "",
    "vrai nature \"c'est ma\"": "",
    "partout chemin": "",
    "rester authentique": "",
    "stay true": "",
    "mode ligne femme": "",
    "rien battre \"ne peut la\"": "",
    "aime \"c'est pour ça qu'on l'\"": "",
    "bon goût région": "",
    "y' bon": "",
    "more fun for everyone": "",
    "dreams fun and inspiration": "",
    "partager amour bon pain": "",
    "engager amour pain": "",
    "bang dire adieu saleté": "",
    "femme oublier \"qu'on n'\"": "",
    "avancer jamais rien lâcher": "",
    "mieux fille \"c'est tellement\" \"d'être une\"": "",
    "devenir vouloir": "",
    "visibly your": "",
    "goût italie": "",
    "master of pasta": "",
    "the chemical company": "",
    "sens ensemble": "",
    "mieux voir mieux vivre": "",
    "expertise force \"c'est sa\"": "",
    "bien penser": "",
    "sharing expertise": "",
    "goûtez bonheur": "",
    "créateur espace": "",
    "for the now generation": "",
    "déchaîner vous": "",
    "sécurité ensemble": "",
    "the feel good place": "",
    "beauté prix accessible": "",
    "bien sucre \"plus que du\"": "",
    "sucre beaucoup idée \"un peu de\"": "",
    "envie bien sucrer": "",
    "télé totalement sport": "",
    "grand spectacle": "",
    "idée fromage": "",
    "sourire partager": "",
    "sharing smile": "",
    "assurance simplifier": "",
    "beal endroit bel histoire": "",
    "prendre apéritif \"et si on\"": "",
    "vie bell": "",
    "séduisant centre commercial": "",
    "centre être invité": "",
    "mode jeu": "",
    "benco démarrer plein pot": "",
    "gourmandise partager": "",
    "united colors of benetton": "",
    "glace meilleur glace": "",
    "enjoyment matter": "",
    "addicted to lover": "",
    "avenir valeur sûr": "",
    "130 an innovation": "",
    "speak with confidence": "",
    "maîtrise eau": "",
    "hôtel singulier": "",
    "stay with people who care": "",
    "parier meilleur": "",
    "no bet no game": "",
    "mieux vivre quotidien": "",
    "quality for men": "",
    "take control": "",
    "profession banquier vocation solidarité": "",
    "banque agent secteur public": "",
    "nouveau chaîne info": "",
    "priorité direct": "",
    "premier chaîne info france": "",
    "banque priver ligne": "",
    "banquier \"c'est moi\"": "",
    "better faster stronger": "",
    "style style vie": "",
    "biactol gagne confiance": "",
    "ciao problème peau": "",
    "laisser vous transporter": "",
    "bibus \"en fait plus\"": "",
    "bic bien": "",
    "argent \"plus pour votre\"": "",
    "avancer ensemble": "",
    "visiter nouveau vie": "",
    "star steak haché": "",
    "cuisine hamburgé": "",
    "roue garde forme": "",
    "only surfer know the feeling": "",
    "aimer action \"pour ceux qui\"": "",
    "banque investisseur \"de tous les\"": "",
    "bineau maison révéler intérieur": "",
    "ami ami": "",
    "maître soin": "",
    "espace vie": "",
    "santé précieux": "",
    "expertise probiotiqu": "",
    "the healing power of life plankton": "",
    "cuisine plaisir": "",
    "meilleur beauté": "",
    "route sécurité": "",
    "satellite astronomique \"n'est plus\"": "",
    "all together now": "",
    "covoiturage confiance": "",
    "partout y route": "",
    "réputation tache blanc couleur": "",
    "côté maman": "",
    "pressing amour propre": "",
    "bijou haut fantaisie": "",
    "idée rafraîchissant fruit mer": "",
    "maximum def experience": "",
    "bus \"plus qu'un\"": "",
    "parler vrai": "",
    "sens profiter \"ça a du\"": "",
    "plaisir conduire": "",
    "distributeur sourire": "",
    "différence bon": "",
    "banca per mondo che cambia": "",
    "banque monde changer": "",
    "banque assurance monde changer": "",
    "immobilier monde changer": "",
    "design danois 1952": "",
    "esthétique métier \"c'est notre\"": "",
    "tv liber tutti": "",
    "améliorer train quotidien": "",
    "experience the extraordinary": "",
    "expérience extraordinaire": "",
    "évolution mobilité": "",
    "bon bonduelle \"quand c'est\"": "",
    "surprendre vous": "",
    "goût bien": "",
    "confiance 1926": "",
    "traditionnellement bon": "",
    "aime \"c'est toi que j'\"": "",
    "meilleur terre": "",
    "it' s": "",
    "valeur \"nous n'avons pas les mêmes\"": "",
    "charcuterie commun": "",
    "bien beau bosch": "",
    "travail pro": "",
    "technologie vie": "",
    "technicité compétitivité qualité service auto": "",
    "better sound through research": "",
    "nouveau mode vie": "",
    "jardin rendre": "",
    "vivre happy technologie": "",
    "bien ensemble": "",
    "idée partager": "",
    "partenaire investir": "",
    "paradis bancaire": "",
    "banque ligne époque": "",
    "banque ligne": "",
    "amour laine": "",
    "ensemble imaginer bien-être": "",
    "envie naître esprit libre": "",
    "bien \"plus pour vous\"": "",
    "créateur mieux vivre": "",
    "nouveau monde": "",
    "communiquer liberté": "",
    "partager liberté": "",
    "faire \"plus pour vous\"": "",
    "we lover technology": "",
    "donner volume parking": "",
    "avoir droit vrai banque": "",
    "servir avenir": "",
    "poste charge": "",
    "let' s do it": "",
    "goûter différence": "",
    "fait valeur": "",
    "bon pouvoir compter brandt": "",
    "construire durer": "",
    "jour \"pour tous les\" \"et même les autres\"": "",
    "sommet nature": "",
    "qualité obstacle prix \"là où la\" \"n'est pas un\"": "",
    "meilleur prix \"et pour le\"": "",
    "concevoir faire différence": "",
    "design desir": "",
    "extend freshnes naturally": "",
    "additionner force multiplier chance": "",
    "instrument for professional": "",
    "cola phare ouest": "",
    "smart technology": "",
    "passer ouest": "",
    "être mieux vrai": "",
    "prix jour \"bas tous les\"": "",
    "essentiel 2 mot": "",
    "bricolage \"près de chez vous\"": "",
    "pro cher": "",
    "envie délice": "",
    "passion excellence": "",
    "route passion": "",
    "source maison": "",
    "water technology": "",
    "your energy expert": "",
    "voyage version original": "",
    "mijoton monde meilleur": "",
    "at your sid": "",
    "business colour": "",
    "bureau y retrouve": "",
    "santé compte \"c'est tout ce qui\"": "",
    "be there": "",
    "respirer bubendorff": "",
    "goûte mauvais marche": "",
    "make the better move": "",
    "grillade qualité métier \"c'est notre\"": "",
    "grillade qualité": "",
    "drive beautiful": "",
    "raviver sens": "",
    "architect of an open world": "",
    "bulldog comprendre homme": "",
    "corps réclame bultex": "",
    "fourniture petit prix": "",
    "préférer goût burger king": "",
    "haver it your way": "",
    "goût \"toujours à mon\"": "",
    "tast is king": "",
    "plein feu goût": "",
    "sentir king \"quand tu te\"": "",
    "spécialiste prix": "",
    "finir surprendre \"on n'a pas\"": "",
    "y retrouve": "",
    " \"toujours là pour vous\"": "",
    "prix vite savoir": "",
    "restez loin \"proche de ceux qui sont\"": "",
    "restez connecter": "",
    "play for real": "",
    "build your dreams": "",
    "trop fort c&amp;a": "",
    "with lover since 1841": "",
    "feel good fashion": "",
    "t. \"tout sous un même\"": "",
    "accélérateur carrière": "",
    "avoir ambition heureux": "",
    "cailleau cailleau cailleau luminaire répondre écho": "",
    "banque aider vivre mieux \"et si une\"": "",
    "banque nouveau définition": "",
    "chausseur passionner": "",
    "caldeo apporte solution énergie": "",
    "lave ling dur calgon \"plus longtemps avec\"": "",
    "heureux bureau \"tout pour être\"": "",
    "progrès vrai": "",
    "changing colors changing live": "",
    "faire choix consommation durable": "",
    "changer monde intérieur": "",
    "garantie résultat": "",
    "poser question avancer": "",
    "vie pose": "",
    "découvrir \"il vous reste tant à\"": "",
    "explorer fin": "",
    "télévision \"le plus de la\"": "",
    "aventure aime": "",
    "vie \"ne suffit pas\"": "",
    "meilleur numérique": "",
    "expert passion \"de toutes vos\"": "",
    "regarder mieux": "",
    "redécouvrir télé": "",
    "victoire canard": "",
    "rien résiste canard": "",
    "changer rien changer \"et c'est ça qui\"": "",
    "you can": "",
    "espace libre créativité": "",
    "partager route succès": "",
    "goût tradition": "",
    "artisanat bâtiment": "",
    "your heart will never leave": "",
    "home of ridiculously good chips": "",
    "croustille carrément succulent": "",
    "people matter results count": "",
    "intérêt lire capital \"on a tous\"": "",
    "avouer payant \"que c'est\"": "",
    "traiteur mer": "",
    "dernier moment pur gourmandise respecte": "",
    "barré \"un pour tous\"": "",
    "barre \"c'est de la\"": "",
    "défendre dignité combattre pauvreté": "",
    "your broadband your way": "",
    "carglass répare carglass remplacer": "",
    "plaisir satisfaction": "",
    "that' s carlsberg": "",
    "monde main \"vous tend la\"": "",
    "the fun ship": "",
    "classe jaune": "",
    "prix plaisir": "",
    "carrefour positif": "",
    "positif \"est de retour\"": "",
    "positif jour": "",
    "prix confiance": "",
    "expert service": "",
    "mieux servir \"c'est de s'en\"": "",
    "prendre futur marche": "",
    "émotion savourer": "",
    "offrir offrir carte or": "",
    "café nommer désir": "",
    "carrément pro": "",
    "maison joyeux maison heureux": "",
    "irremplaçable douceur": "",
    "vivre occasion": "",
    "bien \"parce que c'est vous\"": "",
    "service goût": "",
    "créativité contribution": "",
    "y \"a tout pour moi\"": "",
    "casto y' falloir outil matériau \"a tout ce qu'il\"": "",
    "ensemble faire \"on peut tout\"": "",
    "jour falloir prix \"c'est tous les\" \"qu'il vous\"": "",
    "prendre envol": "",
    "life well travelled": "",
    "être accord \"surtout si vous n'\"": "",
    "plaisir trouver": "",
    "créateur pouvoir achat": "",
    "être riche croyez \"que vous ne le\"": "",
    "économiser plaisir": "",
    "grossiste web": "",
    "avancer avancer": "",
    "prétexte bon": "",
    "être vivre authentique": "",
    "sea more": "",
    "homme \"sont de retour\"": "",
    "émoi chocolat": "",
    "rapprocher nous": "",
    "ensemble vraiment": "",
    "nul part ailleurs": "",
    "bien déco \"plus que de la\"": "",
    "centravet simplifier vie": "",
    "cœur france": "",
    "instinct shopping": "",
    "y connaître bien": "",
    "parler parler bien": "",
    "responsable \"c'est être\"": "",
    "ligne conduite": "",
    "passer végétal \"et si vous\"": "",
    "aimer aime \"comme il vous\"": "",
    "énergie degré \"à tous les\"": "",
    "vie attendre": "",
    "donner confiance crédit": "",
    "faire bouger projet": "",
    "donner avenir projet": "",
    "crédit responsable": "",
    "responsable ensemble": "",
    "best in print": "",
    "formation métier avenir": "",
    "choix acte": "",
    "plus syndical": "",
    "force côté": "",
    "marque satisfaction": "",
    "meilleur info météo": "",
    "demander meilleur thermalisme": "",
    "agir naturellement santé": "",
    "objet idée": "",
    "esprit région": "",
    "alcool fête fou": "",
    "fêter \"même n'importe quoi\"": "",
    "bel chanson français": "",
    "hat' s what we call shopping": "",
    "viande devoir bon \"être toujours aussi\"": "",
    "finir faire aimer viande \"on n'a pas\"": "",
    "saveur énergie": "",
    "terre mer élément réussite": "",
    "naturel faire plaisir": "",
    "odieux divin \"mais c'est\"": "",
    "propreté absolu": "",
    "solution douceur peau": "",
    "salon changer": "",
    "service bien-être": "",
    "creative world in progress": "",
    "no worrie talk happy": "",
    "max relax": "",
    "mode choix prix": "",
    "pardon trop bon \"mais c'est\"": "",
    "committed to comfort": "",
    "the comfort of home without the hassle": "",
    "douceur émotion passion": "",
    "hit battre coeur": "",
    "bel émotion": "",
    "être vrai": "",
    "make it happen": "",
    "route doute": "",
    "découvrir nouveau horizon": "",
    "frais vrai": "",
    "fort chocolat": "",
    "donne goût changer supermarché": "",
    "plaisir sucer": "",
    "compte vie \"pour ce qui\"": "",
    "monde bouger \"parce que le\"": "",
    "construire monde bouger": "",
    "devenir facile": "",
    "dire adieu saleté": "",
    "place évasion": "",
    "good banking is good citizenship": "",
    "monter voir": "",
    "transport collectif choix écologique": "",
    "italien petit quotidien": "",
    "imaginer citroën faire \"pas tout ce que\"": "",
    "créatif technologie": "",
    "sport amp fashion 100 fashion": "",
    "sortie 100 réussir": "",
    "puissance hit": "",
    "donner vie idée": "",
    "avenir écrire \"c'est à vous de l'\"": "",
    "choix clair": "",
    "where getting ready is half the fun": "",
    "saveur ici ailleurs": "",
    "bien manger luxe \"n'est pas un\"": "",
    "vivre briller aimer": "",
    "santé bien surveiller": "",
    "closer \"tout est dans\"": "",
    "shopping marge": "",
    "emmener goût": "",
    "bouger vivre": "",
    "club donne envie sortir": "",
    "trop bon \"c'est juste\"": "",
    "ckac sport": "",
    "plus sport": "",
    "créateur heureux 2000": "",
    "former long vie": "",
    "comptez différence": "",
    "go beyond borders": "",
    "assurer avenir": "",
    "dépasser frontière": "",
    "pouvoir rectifier prix": "",
    "course aime": "",
    "bon saucisson aime \"comme on l'\"": "",
    "esprit sécurité": "",
    "voyager autobus \"c'est votre\"": "",
    "être cœur goût": "",
    "consommer passion": "",
    "crédit téléphone": "",
    "crédit nouveau jour": "",
    "changer regard crédit": "",
    "simplement crédit \"qui vous va\"": "",
    "beau vivre cogedim": "",
    "voir différence": "",
    "profiter vie \"et si on\"": "",
    "transport précision": "",
    "psychologie présent": "",
    "the voice of digital currency": "",
    "we open the way": "",
    "projet \"au plus près de vos\"": "",
    "école voyage": "",
    "entrée créatif": "",
    "get the look": "",
    "sauce devenir art": "",
    "bien vivre cher": "",
    "meilleur prix": "",
    "we live electricals": "",
    "the place to be": "",
    "sourire vie": "",
    "cuisine inviter": "",
    "creating trust onlin": "",
    "loisir bon compagnie": "",
    "grand marque petit prix": "",
    "oser demander lune": "",
    "inspiration technology": "",
    "keep life simple": "",
    "rien arrête": "",
    "fibre entreprise": "",
    "donner envie apprendre": "",
    "informatique avance": "",
    "excellence for complex world": "",
    "pays vie cher": "",
    "bien bien cher": "",
    "bon changer": "",
    "tenir profiter \"qu'à vous d'en\"": "",
    "installe profiter": "",
    "mec \"qui en ont\"": "",
    "magasin innovation": "",
    "erreur aller ailleurs \"c'est d'\"": "",
    "america' s switch": "",
    "america' s energy start here": "",
    "enjoy your life": "",
    "électrõ libre": "",
    "partenaire minceur": "",
    "better together": "",
    "made by you": "",
    "make it your": "",
    " \"pour moi et pour toi\"": "",
    "vie parcours prendre route": "",
    "savoir \"où je vais\"": "",
    "bien impression \"plus que l'\"": "",
    "cora qualité": "",
    "cora confiance": "",
    "nouveau mobilité": "",
    "laisser mer changer idée": "",
    "savoureux nature": "",
    "mobile super facili": "",
    "super facilis": "",
    "commencer demain": "",
    "y être déjà": "",
    "ciel sourire famille": "",
    "ouvrir horizon": "",
    "corse corsicer \"pour nous la\"": "",
    "bel invention argent": "",
    "croisière manquer": "",
    "paradis mer": "",
    "partenaire officiel parent": "",
    "eau minceur courmayeur": "",
    "respirer être livrer": "",
    "restaurant grillade \"de toutes les\"": "",
    "partenaire vétérinaire": "",
    "vivre route confiance": "",
    "people insid": "",
    "penser conduire \"pour ceux qui\"": "",
    "réseau renouveler énergie": "",
    "force réseau": "",
    "get creative": "",
    "mieux vivre demain": "",
    "relation durable changer vie": "",
    "bon sens avenir \"a de l'\"": "",
    "choix \"c'est un\"": "",
    "vision banque": "",
    "côté \"être à vos\"": "",
    "crédit alléger crédit": "",
    "foncièrement vie": "",
    "air large rendre banque \"et si l'\"": "",
    "littoral banque": "",
    "idée social banque": "",
    " \"les uns les autres\"": "",
    "banque \"à qui parler\"": "",
    "vie bel sourire \"quand on lui\"": "",
    "coule source": "",
    "bon \"elle est si\"": "",
    "vivre clarté": "",
    "méditerranée retrouver": "",
    "plein vie": "",
    "croisière métier \"c'est notre\"": "",
    "idée mer": "",
    "goût naturel": "",
    "partout avoir besoin": "",
    "science avenir \"qui pense à notre\"": "",
    "battre \"qui peut te\"": "",
    "the memory expert": "",
    "the memory amp storage expert": "",
    "incruyabl cruque": "",
    "plaisir croustillant": "",
    "futur construction": "",
    "take it everywhere": "",
    "bus nature \"c'est dans ma\"": "",
    "tradition métier cuir": "",
    "faire \"l'un pour l'autre\"": "",
    "savoir faire canapé savoir aimer": "",
    "cuisine donner envie": "",
    "écoute en)vie": "",
    "ensemble donner vie idée": "",
    "meilleur eau": "",
    "contre calcaire culligagne": "",
    "esprit jubil": "",
    "menu fraîcheur esprit santé": "",
    "vélo homme": "",
    "ami prendre curly \"si t'as pas d'\"": "",
    "monde fond curly": "",
    "accro micro": "",
    "contrat performance": "",
    "bon réflexe": "",
    "geste naturel": "",
    "record life": "",
    "habille histoire 1977": "",
    "nouveau grand chaîne": "",
    "exiger payer": "",
    "scandaleusement accessible": "",
    "daddy bien sucre": "",
    "réflexe soulager": "",
    "trancher fraîcheur": "",
    "fast transfer you can trust": "",
    "siècle innovation": "",
    "regarder publier partager": "",
    "énergie quotidien": "",
    "créateur progrès énergétique": "",
    "moment faire bien \"c'est le\"": "",
    "monde lever danette": "",
    "lever danette": "",
    "mieux jour": "",
    "entreprendre santé": "",
    "nourrir faire sourire": "",
    "sortir rue": "",
    "artisan bien-être": "",
    "sentir bien peau": "",
    "bon \"c'est si\"": "",
    "feel good food": "",
    "numéro 1 maroc": "",
    "contrat confiance": "",
    "convenier way to your destination": "",
    "break through": "",
    "aucy y \"si c'est d'\"": "",
    "fin fin extra-fin": "",
    "aucy envie \"si c'est d'\" \"j'en ai\"": "",
    "mourir perdre miette \"que d'en\"": "",
    "prendre meilleur sandwich": "",
    "croquon instant": "",
    "épicerie vrac": "",
    "strength at sea": "",
    "freedom to communicat": "",
    "inutile insister parfait": "",
    "fond forme": "",
    "the safe sid": "",
    "œuvrer demain": "",
    "envie italie": "",
    "vivre italie": "",
    "manger italie": "",
    "vrai nature manga": "",
    "bien acheter bien manger": "",
    "créer envie": "",
    "resto préférer bien livrer": "",
    "incroyable table": "",
    "nouveau garage": "",
    "your is here": "",
    "get more out of now": "",
    "easy dell": "",
    "simplify it": "",
    "pouvoir faire": "",
    "living innovation": "",
    "better everyday": "",
    "énergie côté": "",
    "domotique confort": "",
    "smart control for better world": "",
    "numéro 1 déménageur": "",
    "demeco changer déménagement": "",
    "chaîne compagnon aménageur": "",
    "confiance nom": "",
    "faire voyager meuble": "",
    "mobilité métier \"c'est notre\"": "",
    "agriculture biodynamique": "",
    "tailleur marque": "",
    "service professionnel alimentation": "",
    "conjuguer avoir être": "",
    "coopérer créer avenir": "",
    "bon tuyau": "",
    "passion to perform": "",
    "erleben was verbindet": "",
    "esprit marque": "",
    "chaleur vie": "",
    "libre penser": "",
    "think sofa think dfs": "",
    "making everyday more comfortabl": "",
    "excellence simply delivered": "",
    "we move the world": "",
    "i' m it": "",
    "aller aimer hard discount": "",
    "prix dia \"bas sont chez\"": "",
    "prix dia \"c'est chez\"": "",
    "ordonnance beauté peau": "",
    "peau sain corps sain": "",
    "fuel for life": "",
    "are you alive": "",
    "for successful living": "",
    "your success is built trust": "",
    "the minute": "",
    "dim \"dit tout de vous\"": "",
    "vite très bien": "",
    "efficace ligne \"sur toute la\"": "",
    "y gagner planète": "",
    "énergie cher": "",
    "énergie simplement": "",
    "good deal better": "",
    "sortir quotidien": "",
    "maison prendre vie": "",
    "être original": "",
    "y nouveau télé": "",
    "where dreams come true": "",
    "résistant empire": "",
    "confort jour nuit": "",
    "transport commun": "",
    "you drive we care": "",
    "hier bin ich mensch hier kauf ich ein": "",
    "get ready": "",
    "vivre bien quotidien": "",
    "mordre vie": "",
    "esprit conduire": "",
    "monde douceur": "",
    "manga palpitant": "",
    "éditeur manga palpite": "",
    "get the door it' s domino' s.": "",
    "expert pizza livrer": "",
    "livrer délice cuire four 1960": "",
    "y \"on sait pourquoi on\"": "",
    "vivre esprit libre": "",
    "vriendelijkste internetprovider": "",
    "domotique service": "",
    "intérieur bien": "",
    "vivre intérieur": "",
    "maison toit \"sous le même\"": "",
    "coiffer envie": "",
    "pique oeil évite nœud": "",
    "soin gourmand peau cheveu": "",
    "douceur complice": "",
    "goût éclater monde": "",
    "for the bold": "",
    "doux peau intraitable transpiration": "",
    "qualité meilleur recette": "",
    "spirit of avant-garde": "",
    "serving the entire community": "",
    "dubo dubon dubonnet": "",
    "servir ducro décarcasser \"à quoi ça\"": "",
    "jour décarcasser \"c'est pour tous les\" \"qu'il se\"": "",
    "passion goût": "",
    "décarcasser \"et c'est pour vous\"": "",
    "partager souvenir": "",
    "let' s colour": "",
    "dunkin faire plaisir": "",
    "america runs dunkin": "",
    "dormir tard": "",
    "dormir aimer": "",
    "servir excellence": "",
    "enfant aimer \"ce que les\"": "",
    "nouveau barre goût 3d": "",
    "éditeur caractère(s": "",
    "dur \"c'est celle qui\"": "",
    "y fier partout": "",
    "faire durer plaisir": "",
    "jouer \"à vous de\"": "",
    "préservatif donne envie": "",
    "lover sex durex": "",
    "amour sexe": "",
    "the natural way to relax": "",
    "au-delà temps mode": "",
    "aspirateur perdre aspiration": "",
    "it' s in the game": "",
    "built to resist": "",
    "meilleur occasion": "",
    "occasion confiance": "",
    "vendre simplement": "",
    "the real food company": "",
    "moche marche": "",
    " \"c'est vous\"": "",
    "whatever it is you can get it ebay": "",
    "power to the players": "",
    "finir envie \"on n'a pas\" \"d'en avoir\"": "",
    "entrer ebs sortir hexagone": "",
    "shoe designed to move you": "",
    "ecole créer différence": "",
    "ensemble vivre route": "",
    "place décision": "",
    "prodige eau rose": "",
    "simplement bien": "",
    "real people real lover": "",
    "partenaire informatique quotidien": "",
    "rugby legend": "",
    "élégance match \"est dans le\"": "",
    "fantaisie rigueur": "",
    "avenir choix jours.automobile \"de tous les\"": "",
    "devoir lumière \"plus que la\"": "",
    "donner monde énergie meilleur": "",
    "homme relier homme": "",
    "monde éclair": "",
    "changer énergie ensemble": "",
    "partager excellence": "",
    "makes history by making sense": "",
    "formation projet": "",
    "leder zijn één": "",
    "rien comparable": "",
    "monde cheval": "",
    "luxe luxe \"n'est plus un\"": "",
    "e.leclerc savoir acheter cher": "",
    "cher point \"c'est tout\"": "",
    "défendre compte \"tout ce qui\"": "",
    "vraiment temps téléphoner": "",
    "thinking of you": "",
    "concevoir maison bon vivre \"où il fait\"": "",
    "délicieux lâcher prise": "",
    "inventer nouveau plaisir table": "",
    "monde attention": "",
    "propre action": "",
    "bel idée déchet": "",
    "envie vrai": "",
    "dent vie \"n'ont qu'une\"": "",
    "innovation cœur bien-être": "",
    "star laque": "",
    "micro amp homme": "",
    "rapporte \"et ça leur\"": "",
    "chorizo elpozo": "",
    "we teach english to the world": "",
    "consider it solved": "",
    "hello tomorrow": "",
    "early makers": "",
    "subir agir": "",
    "électricité réseau": "",
    "fournisseur confiance": "",
    "changer monde": "",
    "liberté simplicité fiabilité": "",
    "planète école": "",
    "innovation auditif": "",
    "vie recommencer": "",
    " \"c'est aussi chez vous\"": "",
    "bon \"c'est autrement\"": "",
    "bricolage prix entrepôt": "",
    "fosse tranquille": "",
    "renaître matin": "",
    "beau dormir": "",
    "soin pied spécialité \"c'est notre\"": "",
    "expertise informatique": "",
    "école innovation expertise informatique \"et de l'\"": "",
    "exceed your vision": "",
    "faire meilleur impression": "",
    "comprendre mieux epson": "",
    "faire cheval \"qu'un avec le\"": "",
    "esprit design": "",
    "équipe légende sport": "",
    "partager sport": "",
    "bon vêtement": "",
    "clothe that work": "",
    "élégance naturel": "",
    "cheval jour jour": "",
    "falloir fou dépenser": "",
    "taking you forward": "",
    "world of communication": "",
    "précurseur mode masculin": "",
    "enjoy safer technology": "",
    "plaisir apprendre": "",
    "fraîcheur origine": "",
    "ingénieur \"de tous les possibles\"": "",
    "pièce déménager": "",
    "réhabitez espace": "",
    "maison familial 1926": "",
    "qualité vie commencer ici": "",
    "créateur concept innovant": "",
    "mieux voir monde": "",
    "mettre tigre moteur": "",
    "donner diplôme passion": "",
    "the better vitamin c.": "",
    "école grand projet": "",
    "jour nuit": "",
    "avenir génie": "",
    "génie industrie": "",
    "jeune avenir \"ont de l'\"": "",
    "science peau bel": "",
    "cœur vie entreprise": "",
    "carte maître": "",
    "accepter partout avoir besoin \"où vous en\"": "",
    "assurance téléphone": "",
    "ligne assurance": "",
    "the art of mobilization": "",
    "petit prix grand moment": "",
    "100 pro 100 pneu": "",
    "vie devenir infiniment riche \"et si votre\"": "",
    "for safer car": "",
    "boutique complètement montre": "",
    "you live we care": "",
    "louer voiture \"plus qu'une\"": "",
    "moving your way": "",
    "temps avance": "",
    "plaisant sport \"pas avec le\"": "",
    "chaîne sport europe": "",
    "chaîne sport nouveau génération": "",
    "pari londre trait \"d'un seul\"": "",
    "opening the way": "",
    "choix naturel traverser manche voiture": "",
    "idée piscine": "",
    "poker commencer ici": "",
    "déclarer source jeunesse corps": "",
    "eau boire important air respirer \"parce que l'\"": "",
    "live young": "",
    "art plaire \"une façon d'être\"": "",
    "prepare to explor": "",
    "be first": "",
    "expert profession": "",
    "voyage goût": "",
    "voyage vouloir": "",
    "voyager idée": "",
    "falloir voyager \"tout ce qu'il vous\"": "",
    "expertise énergie climat": "",
    "jour info": "",
    "energy lives here": "",
    "sûr beauté": "",
    "jour chance": "",
    "temps \"d'être soi\"": "",
    "fer faire mieux": "",
    "signe qualité": "",
    "cheval génial": "",
    "you are we": "",
    "passion anime": "",
    "terre mer ciel": "",
    "mieux \"moins c'est\"": "",
    "fabricant optimisme": "",
    "for the game for the world": "",
    "for smooth travelling": "",
    "più responsabili insiem": "",
    "perfection diamant": "",
    "aimer lave vaissell": "",
    "the smart shoes": "",
    "façon éveiller \"mille et une\"": "",
    "bel vie \"elle est pas\"": "",
    "savoir goûter vie": "",
    "obsession bon": "",
    "nouveau bien manger": "",
    "faire mieux manger mieux \"pour que vous\"": "",
    "plaisir intensément": "",
    "histoire goût \"entre nous et vous\" \"c'est une\"": "",
    "fluncher mieux manger": "",
    "y' flunch fluncher \"a que chez\" \"qu'on peut\"": "",
    "certifier non conforme": "",
    "agitateur curiosité": "",
    "adhérer \"on ne peut qu'\"": "",
    "bon curieux": "",
    "cube carrer": "",
    "agir logement": "",
    "syndicalisme solution": "",
    "the spirit of sound": "",
    "fou envie": "",
    "bien meilleur réveiller": "",
    "lire loin": "",
    "référence habitat": "",
    "défenseur habitat": "",
    "feel the difference": "",
    "monter bord": "",
    "go further": "",
    "calling all curiou": "",
    "rouler faire": "",
    "être bien vacance": "",
    "vacance français": "",
    "plaisir grand": "",
    "grand marque côté": "",
    "air vif france 2": "",
    "évènement rassemble": "",
    "2 passion": "",
    "différence rassembler": "",
    "télé prendre temps": "",
    "comprendre mieux": "",
    "finir surprendre \"elle n'a pas\"": "",
    "4 fois ensemble": "",
    "faire connaissance": "",
    "vivre bleu mieux": "",
    "louer liberté": "",
    "foot foot \"quand on parle de\" \"on parle de\"": "",
    "point ouvrir info": "",
    "clair \"et tout est plus\"": "",
    "écouter rien voir \"ça n'a\"": "",
    "stimule esprit sublime corps": "",
    "aller do ré": "",
    "allié avenir": "",
    "mutuelle avance": "",
    "télévision france": "",
    "chaîne métis": "",
    "avoir choix": "",
    "choix différence": "",
    "créer partager": "",
    "télé change pub": "",
    "cuisinez aimer": "",
    "origine y francine": "",
    "ensemble accélérer expertise": "",
    "vivre goût jour": "",
    " \"à deux pas\" \"tout est là\"": "",
    " \"c'est tout compris\"": "",
    "liberté prix \"n'a pas de\"": "",
    "free \"il a tout compris\"": "",
    "partenaire it": "",
    "histoire poursuivre": "",
    "sport vrai": "",
    "tigre \"est en toi\"": "",
    "vivre légèreté": "",
    "prendre santé cœur": "",
    "muscler \"c'est plus\"": "",
    "vélo quotidien": "",
    "high connexion": "",
    "shaping tomorrow with you": "",
    "we make sur": "",
    "soul and dance": "",
    "réseau courtier": "",
    "media with passion": "",
    "monde exaltant": "",
    "dépenser aller loin": "",
    "musique chose": "",
    "music for happy people": "",
    "préféré italien": "",
    "gusto italiano": "",
    "centre mode": "",
    "mode voir fort": "",
    "probablement meilleur lait \"après le vôtre\" \"l'un des\"": "",
    "now you' re playing with portable power": "",
    "puissance creux main": "",
    "vie jeu": "",
    "génération digital": "",
    "esprit libre avancer \"c'est avec l'\"": "",
    "assurer avancer": "",
    "no bullshit": "",
    "alchimie botanique futur": "",
    "voyagez mieux arriver heureux": "",
    "prendre soin": "",
    "take care": "",
    "mieux énergiser mieux performer": "",
    "boite esprit ouverture": "",
    "cinéma existe \"depuis que le\"": "",
    "tradition amp innovation": "",
    "signature grand fabricant meuble": "",
    "brin légèreté": "",
    "vie bleu": "",
    "géant \"et c'est pour vous\"": "",
    "repas devenir géant": "",
    "fondation finition": "",
    "vivre énergie": "",
    "security to be free": "",
    "prêt demain": "",
    "jeune amp joaillier": "",
    "accent mode accent prix": "",
    "mode aime \"c'est la\"": "",
    "prix permanence": "",
    "fin lunette cher": "",
    "bien entouré": "",
    "we logistic your growth": "",
    "chaussure respire": "",
    "expert diététique": "",
    "partir bien grandir": "",
    "menthe \"seulement de la\"": "",
    "intérim zen \"de a à\"": "",
    "ensemble gagner sommet": "",
    "good hair day every day": "",
    "salubrité universel": "",
    "culture revendre": "",
    "culture échange \"c'est l'\"": "",
    "occasion \"c'est l'\"": "",
    "idée génie": "",
    "the mobile network run by you": "",
    "affaire or": "",
    "envie petit prix": "",
    "real american hero": "",
    "setting the standard": "",
    "perfection masculin": "",
    "chaude boisson froid": "",
    "aller bien ici": "",
    "voyager grand besançon": "",
    "haver nice day": "",
    "aime jamais trop \"on n'en fait\"": "",
    "vérité goût": "",
    "trouver point g.": "",
    "meilleur progrès": "",
    "social coding": "",
    "meilleur manga": "",
    "lettre dire long": "",
    "calibre professionnel": "",
    "assurément humain": "",
    "bien vivre": "",
    "it' s go tim": "",
    "compétence prix": "",
    "conduire grand": "",
    "don' t be evil": "",
    "be hero": "",
    "marque temps": "",
    "vivre sport": "",
    "révéler vous": "",
    "choix prix simplicité": "",
    "magazine homme \"qui parle aux\" \"sur un autre ton\"": "",
    "ciel avenue": "",
    "partager jouer": "",
    "europe invente": "",
    "meilleur marché": "",
    "grand'mère faire bon café": "",
    "communauté urbain amp humain": "",
    "regard oeil": "",
    "rien trop grand": "",
    "territoire avenir": "",
    "territoire créatif numérique durable": "",
    "shopping facile": "",
    "shopping \"c'est plus que du\"": "",
    "gardener of chocolate": "",
    "parier jamais manger \"que vous n'en\"": "",
    "stand together": "",
    "the real driving simulator": "",
    "force nature": "",
    "choisir gaz choisir avenir \"c'est aussi\"": "",
    "all time classic": "",
    "professionnel confiance": "",
    "emmener -t il": "",
    " \"on va de l'avant\"": "",
    "werkt voor iedereen": "",
    "gelato come una volta": "",
    "high tech low cost": "",
    "you move we care": "",
    " \"toujours là pour moi\"": "",
    "faire face risque": "",
    "vrai vie assure ici": "",
    "décider ensemble vivre mieux": "",
    "jour meilleur": "",
    "nourrir monde diversité": "",
    "faire route ensembl": "",
    "qualité santé assiette": "",
    "collective buying power": "",
    "for good reason": "",
    "être unique conducteur": "",
    "parler bébé": "",
    "garder contact": "",
    "for safer world": "",
    "bon énergie": "",
    "créateur émotion partager": "",
    "immobilier garanti": "",
    "door door amsterdam": "",
    "style vie": "",
    "tast the best": "",
    "voyage sens": "",
    "pur plaisir": "",
    "is where your home is": "",
    "squat ado": "",
    "design esprit \"a de l'\"": "",
    "design ami": "",
    "fly your dreams": "",
    "the people who give you extra": "",
    "mode halle \"sont à la\"": "",
    "rendre monde beau \"et si c'était vous qui\"": "",
    "français joli": "",
    "the smart solution": "",
    "shaping time since 1892": "",
    "driving emotion": "",
    " \"de vous et pour vous\"": "",
    "vrai pouvoir h.a": "",
    "déjà mieux \"et ça va\"": "",
    "the quality people in yachting": "",
    "breaking rule setting trend": "",
    "digital art digital life": "",
    "achat cash prix": "",
    "journal bête méchant": "",
    "pouvoir acheter voler \"si vous ne\"": "",
    "haribo beau vie grand petit": "",
    "harmonie santé": "",
    "avançon collectif": "",
    "place expert": "",
    "pétrir bon invention": "",
    "idée donner idée": "",
    "goût \"t'as du\"": "",
    "burger \"à chacun son\"": "",
    "it' s beautiful thing": "",
    "bien rire": "",
    "voir ailleurs voir havre": "",
    "voir ville": "",
    "perfection image \"et du son\"": "",
    "the power of you": "",
    "expression contre pellicule": "",
    "bien tête": "",
    "vivre pleinement vie": "",
    "vivre hésitation": "",
    "making every journey better": "",
    "nouveau lignée gestionnaire": "",
    "apprendre oser": "",
    "changer appli vtc": "",
    "esprit bière heineken": "",
    "so refreshing": "",
    "serving the planet": "",
    "be fresh": "",
    "open your world": "",
    "histoire hélicoptère porte nom": "",
    "allié contre toux": "",
    "faire ressortir meilleur": "",
    "cliquer nettoyer": "",
    "qualité henkel": "",
    "qualité amp responsabilité": "",
    "excellenc i our passion": "",
    "makes delivery easy": "",
    "goût chose simple": "",
    "matin essentiel": "",
    "solution crédit facile vivre \"d'un seul\"": "",
    "hextril enlever mal bouche": "",
    "performance fiabilité": "",
    "empower your digital business": "",
    "grand envie viande restaurant": "",
    "amour viande": "",
    "bœuf nul part ailleurs": "",
    "hippo \"à chacun son\"": "",
    "steak house français": "",
    "suite \"pour toujours et pour tout de\"": "",
    "histoire bijou": "",
    "inspire the next": "",
    "qualität die man schmeckt": "",
    "construire avenir": "",
    "get closer": "",
    "bière trouble esprit clair": "",
    "signature of excellence": "",
    "savor the journey": "",
    "fraîcheur vivre": "",
    "make house home": "",
    "more saving more doing": "",
    "home owner helping homeowner": "",
    "solide conseil expert inclure \"c'est du\"": "",
    "the power of dreams": "",
    "puissance rêve": "",
    "simple bon": "",
    "for the brave": "",
    "faire saut région \"à l'autre\"": "",
    "y être": "",
    "trouver endroit parfait": "",
    "choix évident": "",
    "idée maison": "",
    "passer temps faire course \"et si vous\" \"à ne plus\"": "",
    "cybermarché service envie": "",
    "bien y houra": "",
    "the computer is personal again": "",
    "make it matter": "",
    "donner importance": "",
    "keep reinventing": "",
    "pro impôt": "",
    "banque partout monde": "",
    "the world' s local bank": "",
    "engineering mobility": "",
    "quietly brilliant": "",
    "bold authentic and playful": "",
    "let' s simply share": "",
    "connexion avance": "",
    "y huggies": "",
    "protéger engager \"c'est s'\"": "",
    "aventure humain": "",
    "maîtriser nature": "",
    "ready when you are": "",
    "mehr als ein ziel": "",
    "expert peau sec": "",
    "conseiller vaincre": "",
    "rouler aimer": "",
    "true quality matters": "",
    "choisir brillamment": "",
    "new thinking new possibilitie": "",
    "nouveau idée nouveau possibilité": "",
    "voir loin": "",
    "jour jour \"comme au premier\"": "",
    "hôtel aime \"comme on les\"": "",
    "signe particulier": "",
    "solution petit planète": "",
    "donner vie ville": "",
    "immobilier futur \"de tous vos\"": "",
    "traitement air métier": "",
    "food you can trust": "",
    "more for your money": "",
    "design with gaming in mind": "",
    "internet idée": "",
    "body amp mind": "",
    "beautiful user of space": "",
    "marque second main informatique": "",
    "chaîne numéro 1": "",
    "choisir voyager \"avec qui vous\"": "",
    "bringing something special to the table": "",
    "vif bouffe": "",
    "bon iglo": "",
    "y curieux \"parce qu'il\" \"a des gens plus\" \"que d'autres\"": "",
    "information grandeur nature": "",
    "home is the most important place in the world": "",
    "bien marchand meuble \"plus qu'un\"": "",
    "happy insid": "",
    "vif vie maison": "",
    "latitude vie": "",
    "demain invente ici": "",
    "voyage émotion": "",
    "archipel caractère": "",
    "y moment vie change mieux": "",
    "y croire": "",
    "enseigne immobilier": "",
    "site vouloir logement neuf \"de ceux qui\"": "",
    "clic emploi": "",
    "monde marche": "",
    "travailler vivre": "",
    "we work you play": "",
    "making space for the futur": "",
    "performance inspirer": "",
    "sublimer conduite": "",
    "entreprendre confiance": "",
    "créateur intérêt": "",
    "argent heureux \"là où votre\"": "",
    "banque \"doit être comme ça\"": "",
    "intérêt compte \"c'est votre\"": "",
    "save your money": "",
    "améliorer banque": "",
    "bon décider": "",
    "inspiring progress": "",
    "prendre loisir très sérieux": "",
    "fruit nus": "",
    "bon \"et en plus c'est\"": "",
    "bon côté chose": "",
    "gagne innover": "",
    "mesurer comprendre": "",
    "repartir bon pied": "",
    "you' r back": "",
    "leap ahead": "",
    "partenaire futur": "",
    "look insid": "",
    "experience what' s insid": "",
    "together again": "",
    "jour simplement": "",
    "payer flash": "",
    "être futé payer": "",
    "manger bœuf manger bœuf": "",
    "livre vouloir bien": "",
    "semer fleur récolte tendresse": "",
    "messager émotion": "",
    "hôtelier accent": "",
    "mousquetaire distribution": "",
    "uni contre vie cher": "",
    "prendre longueur avance": "",
    "sport commencer ici": "",
    "intersport très fort": "",
    "beau chaud cher": "",
    "connecting opportunitie": "",
    "donner sens voix": "",
    "document to knowledge": "",
    "laisser vous emporter": "",
    "making robot work for you": "",
    " \"plus proche de vous\"": "",
    "bien commencer vie": "",
    "fièrement halal": "",
    "isolation responsable": "",
    "partez loin prévoir": "",
    "vrai morceau pays basque": "",
    "excellence statistique": "",
    "étudier construire maintenir": "",
    "open your mind": "",
    "info rapproche": "",
    "passer 24 heure 24 \"là où ça se\"": "",
    "info plus": "",
    "info temps": "",
    "cœur actualité": "",
    "information grand i.": "",
    "information arrête jamais": "",
    "beauoup loin itineri": "",
    "making it personal": "",
    "qualité prix": "",
    "recette bonheur": "",
    "passer vitesse supérieur": "",
    "café monde plaisir": "",
    "petit \"plus en plus\"": "",
    "how alive are you": "",
    "irish spirit": "",
    "pureté prix \"n'a pas de\"": "",
    "dynamique froid": "",
    "voyage commencer ici": "",
    "découvrir liberté": "",
    "faire pousser idée": "",
    "ici terre idée": "",
    "good times start here": "",
    "vitrine monde": "",
    "trouve ami": "",
    "naturellement chocolat": "",
    "you above all": "",
    "télé déchaîne héros": "",
    "série culte \"on a tous une\"": "",
    "cybermarché bureau": "",
    "juva bien juvamine": "",
    "expérience parfait": "",
    "partenaire quotidien linge": "",
    "idée cadeau": "",
    "bonheur carte": "",
    "avance envie": "",
    "find your rhythm enjoy your run": "",
    "true service": "",
    "esprit manga": "",
    "kandoo \"c'est moi qui fait tout\"": "",
    "makes difference": "",
    "faire différence": "",
    "let the good time roll": "",
    "want it keep it": "",
    "enfant grandir trop vite kellogg' s grandir bien": "",
    "matin réussir journée sourire": "",
    "retrouve petit déjeuner": "",
    "rendez-vous petit déjeuner": "",
    "interim spécialiste": "",
    "solution beauté": "",
    "recette gourmand": "",
    "tasse parfait": "",
    "tast the difference": "",
    "finger lickin good": "",
    "so good": "",
    "it' s finger lickin good": "",
    "fois khüne": "",
    "mode petit prix": "",
    "histoire amour": "",
    "plaisir petit faim": "",
    "gâteau rêver goûter": "",
    "surprise aller vous inventer": "",
    "petit grand gagnant": "",
    "lover bread lover kinsbrill": "",
    "fromage gastronome culotte court": "",
    "frer grave \"mais c'est pas\"": "",
    "changer cuisine changer": "",
    "haver break haver kit kat": "",
    "bon boule \"d'avoir les\"": "",
    "jamais court idée": "",
    "donner saveur vie": "",
    "photo réussir cas \"dans tous les\"": "",
    "avancer imagination": "",
    "partager \"on a tant à\"": "",
    "conseil jusque bout": "",
    "coeur immeuble": "",
    "dedicated to people flow": "",
    "giving shape to idea": "",
    "sonne bien": "",
    "joli pire \"je ne suis pas\"": "",
    "excellence in flight": "",
    "coupable bon": "",
    "suède croustillant \"ce que la\" \"a de plus\"": "",
    "croquez craquer": "",
    "service bière": "",
    "bel voir": "",
    "aller aimer": "",
    "source étiquetage": "",
    "plaisir état esprit": "",
    "dédier plaisir": "",
    "cf. crosse technology": "",
    "essentiel lactel": "",
    "essentiel mieux": "",
    "matériau construire monde": "",
    "matériau cœur vie": "",
    "sûrement mieux somnifère": "",
    "élégance tempérament": "",
    "croire beauté": "",
    "résister luxe \"à un tel\"": "",
    "y \"en a pas deux\"": "",
    "beau projet \"c'est le vôtre\"": "",
    "lapeyre maison lapeyre solution": "",
    "savoir bien faire": "",
    "dictionnaire larousse \"on ne dit plus un\"": "",
    "émotion commencer ici": "",
    "découvrir vie rose": "",
    "café favori italien": "",
    "bonheur simple": "",
    "bouchée amour \"et c'est l'\"": "",
    "lay' s adore": "",
    "information continue lci": "",
    "mieux savoir comprendre": "",
    "être cœur info": "",
    "vivre république": "",
    "politique vrai": "",
    "aime faire gagner": "",
    "prix qualité": "",
    "goût vivre cher": "",
    "choix malin vivre bien": "",
    "plaisir \"est pour vous\"": "",
    "vendre acheter \"près de chez vous\"": "",
    "leclerc clair": "",
    "building partnerships": "",
    "leerdamer malheur \"ou je fais un\"": "",
    "goût malheur": "",
    "générateur croissance durable": "",
    "bien lefert mieux": "",
    "moment saveur": "",
    "révélation date 1240": "",
    "bière culte 1240": "",
    "if it isn' t fresh it isn' t legal": "",
    "imaginer \"à toi d'\"": "",
    "valoir rien mieux meilleur": "",
    "rebuild the world": "",
    "where vision gets built": "",
    "back to basics": "",
    "habiller vous plaisir": "",
    "for those who do": "",
    "smarter technology for all": "",
    "change the way you see disability": "",
    "grand nom camembert": "",
    "envie prendre vie": "",
    "projet loin": "",
    "erreur lesieur": "",
    "original never fits": "",
    "go forth": "",
    "the pursuit of perfection": "",
    "futur main \"est entre vos\"": "",
    "conquête perfection": "",
    "fraîcheur transporter": "",
    "life' s good": "",
    "prendre temps avance télépéage": "",
    "idéal lidl": "",
    "vrai prix bon chose": "",
    "liebig mettre cœur légume": "",
    "sommeil marque": "",
    "amour \"de l'autre\"": "",
    "net sens propre": "",
    "passion finesse": "",
    "connexion perfection": "",
    "supercentre mode maison": "",
    "monde intérieur": "",
    "ligne commun \"on a tous une\"": "",
    "transport mobilité urbain": "",
    "vital actif": "",
    "anything is": "",
    "réveiller lion \"qui est en vous\"": "",
    "rugir plaisir": "",
    "tea can do that": "",
    "be more tea": "",
    "oeil mériter lissac": "",
    "for the journey": "",
    "don' t lose it locat it": "",
    "annuaire internet région": "",
    "prévenir bouger retrouve \"dit où ça se\"": "",
    "be brillier together": "",
    "hôtellerie visage humain": "",
    "créer beau loisir \"c'est le plus\"": "",
    "feel safe at home": "",
    "elegance is an attitude": "",
    "that' s what like": "",
    "vacance volonté": "",
    "relooker vous": "",
    "rater chercher lettre oréal": "",
    "monde ouverture": "",
    "imagine the freedom": "",
    "besoin pause lotu \"on a tous\"": "",
    "meilleur brebis": "",
    "never improving": "",
    "y paquet énergie paquet lire": "",
    "lire approuver": "",
    "ouvrir champ": "",
    "it' s toasted": "",
    "there' s no better way to fly": "",
    "y bel envoler \"a pas plus\" \"façon de s'\"": "",
    "redécouvrir nature riz": "",
    "manger bon manger bien lustucru naturellement": "",
    "mordu lustucru": "",
    "always with you": "",
    "appeler monde cher": "",
    "go get it": "",
    "mal passer": "",
    "voir m6 \"c'est à\" \"c'est sur\"": "",
    "petit chaîne monte monte": "",
    "20 an cultiver différence": "",
    "futur vivon ensemble": "",
    "partir durer": "",
    "profil \"t'as le\"": "",
    "référence qualité prix": "",
    "voir vraiment mieux brûlure estomac": "",
    "gagner solidaire \"on a tous à\"": "",
    "solidarité force": "",
    "sport \"à chacun son\"": "",
    "bouger bus": "",
    "grand magasin homme": "",
    "cuisinez vous vie meilleur": "",
    "savoure repas \"plus qu'un\"": "",
    "architecture made simple": "",
    "meilleur bd féminin": "",
    "assureur militant": "",
    "y maille aller": "",
    "piano piano buono buono": "",
    "numéro 1 sommeil": "",
    "dormir largement mieux": "",
    "plaisir intérieur": "",
    "petit secret gâteau léger moelleux": "",
    "maïzena cuisine mieux": "",
    "univers aventure": "",
    "y' marre y' malabar": "",
    "prendre télé avance": "",
    "y \"a que toi qui me fais ça\"": "",
    "mammouth écrase prix": "",
    "être vous prêt autant plaisir": "",
    "smart = sexy": "",
    "créateur solution emploi": "",
    "malin maped": "",
    "cf. u système": "",
    "histoire dessert": "",
    "unique \"ce qui est\" \"c'est vous\"": "",
    "beauté ressemble": "",
    "droit voyage": "",
    "bien repérer bien acheter": "",
    "prendre meilleur": "",
    "consommer mieux décide": "",
    "travail repos plaisir": "",
    "rêver partir": "",
    "apéritif renommée mondial": "",
    "make lover happen": "",
    "dormir matelsom": "",
    "heure bien dormir \"il est l'\"": "",
    "façon aimer fruit": "",
    "accelerating the pace of engineering and science": "",
    "bon ½ufs oeil fermer": "",
    " \"elles ont tout pour elles\"": "",
    "faire course \"l'autre façon de\"": "",
    "animal \"tout pour vos\"": "",
    "3d for the real world": "",
    "site communautaire devenir clair": "",
    "décidément zoom zoom": "",
    "zoom zoom": "",
    "vroum vroum": "",
    "au-delà convention": "",
    "the anti-sho": "",
    "y magie mccain \"a de la\"": "",
    "consommer préférence \"avant les autres\"": "",
    "manger \"c'est ceux qui en parlent le moins qui en\"": "",
    "it' s all good": "",
    "aime \"c'est tout ce que j'\"": "",
    "venir être": "",
    "m. \"c'est ce que j'\"": "",
    "learn more do more": "",
    "chaîne musical": "",
    "crédit sens service \"qui a le\"": "",
    "crédit prête attention \"aussi de l'\"": "",
    "crédit parler -en simplement": "",
    "vie crédit": "",
    "voir grand rencontre": "",
    "start something real": "",
    "i' m watchin it": "",
    "y for young": "",
    "is it live or is it memorex": "",
    "instant précieux": "",
    "déclic fraîcheur": "",
    "pansement héros": "",
    "keeping score of entertainment": "",
    "we deal with criticism": "",
    "temps clic": "",
    "portée temps": "",
    "planifier temps": "",
    "météo compte vraiment": "",
    "référence météo québec": "",
    "centre météo québec": "",
    "qualité forcément cher \"n'est pas\"": "",
    "never out of style": "",
    "quality built in": "",
    "chanson préférer": "",
    "radio aime": "",
    "music smile": "",
    "100 musique français": "",
    "santé priorité": "",
    "trublion goût": "",
    "meilleur avancer": "",
    "génération jeu vidéo": "",
    "potentiel passion": "",
    "be what' s next": "",
    "livraison ponctuel garantie": "",
    "fois mieux": "",
    "immer besser": "",
    "top pops": "",
    "m meilleur": "",
    "rester léger": "",
    "world class protein solution": "",
    "be mini": "",
    "explor more": "",
    "passion café": "",
    "lorrain direct": "",
    "affaire bon sens \"c'est une\"": "",
    "bon deal mistergooddeal": "",
    "change for the better": "",
    "100 soleil": "",
    "zéro tracas zéro blablas": "",
    "bonheur assurer \"c'est le\"": "",
    "entrepreneur assurance": "",
    "faire tourner": "",
    "meuble falloir \"qu'il vous\"": "",
    "stockage déplacer place": "",
    "offrir mobilité stockage": "",
    "téléphonie devenir simple": "",
    "lover work play": "",
    "beau cadeau": "",
    "donne \"on vous en\"": "",
    "marché floral 1965": "",
    "mot amour chocolat": "",
    "concevoir durer": "",
    "carte porte-monnaie": "",
    "bon faire confiance femme \"c'est si\"": "",
    "frappe monnaie esprit": "",
    "petit magasin manqu rien": "",
    " \"on fait quoi pour vous aujourd'hui\"": "",
    "ville y vie": "",
    "obtenir douceur \"tout par la\"": "",
    "monsieur aime \"c'est tout ce que\"": "",
    "contrat confort": "",
    "nouveau vie appeler": "",
    "trouver mieux": "",
    "mieux valoir manger": "",
    "tailler canada tailler": "",
    "one client at time": "",
    "fresh choice for you": "",
    "expérience transporte": "",
    "intelligence everywher": "",
    "life motorola powered": "",
    "coopérative plein air": "",
    "bien frais": "",
    "glaçon friandis": "",
    "take good care": "",
    "magie puissance \"c'est sa\"": "",
    "falloir \"plus qu'il n'en\"": "",
    "innovation with style": "",
    "trouver simple battement aile": "",
    "going your way": "",
    "bienvenue point vue \"à tous les\"": "",
    "dialoguer culture": "",
    "vision manga": "",
    "déjà mieux": "",
    "esprit solidarité": "",
    "play with it": "",
    "your life": "",
    "grand méchant look": "",
    "world class sound": "",
    "être sûr porter nana": "",
    "chose \"que les autres n'ont pas\"": "",
    "we' re juice guy": "",
    "artisan rêve": "",
    "suivre goût": "",
    "journée \"ça fait ma\"": "",
    "vivre heureux vivon curieux": "",
    "it' s how you live": "",
    "mer terre": "",
    "entraîne résultat": "",
    "mobilité essentiel": "",
    "setting standard for excellence": "",
    "we valoir your mail": "",
    "opticien jusque bout oeil": "",
    "simply enjoy": "",
    "what else": "",
    "café corps âme": "",
    "énorme envie \"on en a une\"": "",
    "nestea goût nestea": "",
    "used car you can rely": "",
    "loin vouloir": "",
    "everything by everyone": "",
    "the way to go": "",
    "voices that matter": "",
    "every day in whole new way": "",
    "hey you never know": "",
    "enjoy the ride": "",
    "printemps année \"c'est le\"": "",
    "cigarette y solution nicorett": "",
    "just do it": "",
    "at the heart of the image.mettez nikon vie \"un peu de\"": "",
    "photography first": "",
    "intelligent amusant \"plus c'est\" \"plus c'est\"": "",
    "vrai jeu puissance \"c'est le\"": "",
    "shift_th way you move": "",
    "made in qualité": "",
    "innover exalter": "",
    "innovation that excite": "",
    "beauté nivéa": "",
    "imaginer beauté": "",
    "beauté libérer": "",
    "connecting people": "",
    "together we' re uniting communitier": "",
    "y' vrai vie vie \"a pas que la\"": "",
    "mobility expert": "",
    "avoir priorité": "",
    "demain entretenir": "",
    "voir danger voir loin": "",
    "driven by your city": "",
    "bienvenue être": "",
    "dur éteindre \"c'est de l'\"": "",
    "hit music only": "",
    "nouveau radio jeune": "",
    "génération spontané": "",
    "télé généraliste urbain": "",
    "nouveau télé \"qui fait parler d'elle\"": "",
    "réfléchir numérique": "",
    "monter puissance": "",
    "falloir énergie enfant \"pour être un\"": "",
    "jour bonheur tartiner \"c'est du\"": "",
    "the way it' s meer to be played": "",
    "we' re better connected": "",
    "beau océdar": "",
    "chaîne odyssée": "",
    "joie bel": "",
    "taking care of business": "",
    "presse réserver monde éducation": "",
    "petit bout histoire": "",
    "passion sushi": "",
    "bon conduite": "",
    "best answer": "",
    "bien peau \"d'être dans sa\"": "",
    "ici régner qualité": "",
    "fête boîte jaune \"c'est la\"": "",
    "y ambiance boîte jaune \"a de l'\"": "",
    "job expérience vie \"plus qu'un\"": "",
    "imaginatif sight sound": "",
    "enter new dimension": "",
    "découvrir opel": "",
    "wir leben auto": "",
    "avenir appartenir": "",
    "clair net optinett": "",
    "brosse dent expert": "",
    "rejoindre mouvement": "",
    "futur aimer": "",
    "loin ensemble": "",
    "together we can do more.la vie changer orange": "",
    "rapprocher essentiel": "",
    "falloir bien secouer orangina pulpe \"elle reste en bas\"": "",
    "naturellement pulpeux": "",
    "shake the world": "",
    "profession idée engagement": "",
    "connexion monde": "",
    "radio rock": "",
    "libre rock": "",
    "dynamite \"c'est de la\"": "",
    "save more earn easier": "",
    "write it show it": "",
    "talent envie \"c'est d'avoir\"": "",
    "power in your hand": "",
    "gagner tard tard \"maintenant et plus\"": "",
    "enveloppe protéger forêt": "",
    "amour table autour \"et des gens\"": "",
    "ordinateur comprendre homme \"c'est à l'\"": "",
    "your digital playground": "",
    "site passionné cheval \"de tous les\"": "",
    "paradise yourself": "",
    "ivresse fruit": "",
    "numéro 1 pointure extrême": "",
    "aider mobilité": "",
    "inspirer bébé": "",
    "aimer dormir jouer": "",
    "ideas for life": "",
    "idée vie": "",
    "mettre épreuve \"le à l'\"": "",
    "the power of color.because the world isn' t black and white.where color come from.th color of ideas.love color": "",
    "pâte pâte oui panzani": "",
    "être libre": "",
    "better ingredient better pizza": "",
    "meilleur ingrédient meilleur pizza": "",
    "rire idée fixe": "",
    "irréductible parc": "",
    "prendre bol air vrai": "",
    "ici sortie": "",
    "poids mot choc photo": "",
    "vie histoire vrai": "",
    "pouvoir rallumer télé": "",
    "télé esprit large petit écran \"qui a l'\"": "",
    "rêver grand": "",
    "opérateur pro": "",
    "esprit côté ouest": "",
    "move wireless": "",
    "générateur vie meilleur": "",
    "être partie": "",
    "bon \"parce que c'est\"": "",
    "fixe refix": "",
    "voix maître": "",
    "ca tenir fort": "",
    "fort \"ça rend plus\"": "",
    "faire je": "",
    "chemin goût": "",
    "gourmand nature": "",
    "always learning": "",
    "chien rayonnant santé": "",
    "affaire chien": "",
    "moyen facile voler": "",
    "bière caractère": "",
    "aller adorer": "",
    "what know how can do": "",
    "complètement choco pépito": "",
    "ici pepsi": "",
    "plein idée bien manger": "",
    "yaourt beaucoup doux \"ce n'est pas un\"": "",
    "extincteur soif": "",
    "servir imaginer vêtement rien faire \"à quoi ça\" \"si on ne peut\"": "",
    "vêtement faire faire chose": "",
    "jamais vieux": "",
    "enfant vrai": "",
    "jamais manquer ressource": "",
    "épicier type formidable": "",
    "enfant \"ce n'est que pour les\"": "",
    "bon goût large": "",
    "bon simplicité \"que c'est\"": "",
    "mer inspire": "",
    "grandir imagination": "",
    "petro station ici \"des gens d'\"": "",
    "racine force \"c'est ma\"": "",
    "happiness in store": "",
    "idée pharmacie": "",
    "croquer monde": "",
    "bon suite": "",
    "sens and simplicity": "",
    "faire mieux": "",
    "innovation and you": "",
    "mobile meilleur prix": "",
    "idée monde objet ailleurs": "",
    "traiteur intraitable": "",
    "partout france bel": "",
    "heureux ensemble": "",
    "envie vacance": "",
    "ca pique arrache": "",
    "mettre mot bouche": "",
    "maîtrise puissance rien": "",
    "regarde poche prendre pitch": "",
    "contrat achat tranquille": "",
    "gagner course \"sur toutes vos\"": "",
    "histoire jeu vidéo main": "",
    "bon chaud \"comme c'est\"": "",
    "partager urgence": "",
    "trop bon trop hut": "",
    "prendre goût plaisir": "",
    "meilleur découverte": "",
    "fin fin planter fin": "",
    "malin main \"t'es plus\"": "",
    "histoire \"en avant les\"": "",
    "this is living": "",
    "donner meilleur carrément": "",
    "nouveau vie nouveau envie": "",
    "habitat cadre vie": "",
    "être sûr": "",
    "protéger avoir cher \"ce que vous\"": "",
    "réponse professionnel": "",
    "expert prix": "",
    "stress y point s.": "",
    "sourire être bronzer": "",
    "soleil métier": "",
    "économie durable": "",
    "démocratie participatif": "",
    "croquer vie plein dent": "",
    "innovant nature": "",
    "génie classe": "",
    "sandwich reproche": "",
    "gotta catch em all": "",
    "qualité durablement": "",
    "raffiné ligne \"sur toute la\"": "",
    "bienvenue pays noir couleur": "",
    "partout jusque": "",
    "énergie positif": "",
    "savoir peser": "",
    "préférence crédit": "",
    "bien manger début bonheur \"c'est le\"": "",
    "plaisant plaisir \"parce qu'on ne\" \"pas avec le\"": "",
    "prendre vie côté plaisir": "",
    "décompresser boire manger": "",
    "achat vente garanti": "",
    "petit prix sourire": "",
    "énergie devenir force": "",
    "réflexe gentillesse": "",
    "vie marque": "",
    "mieux école \"et ça va tellement\"": "",
    "énergie capter essentiel": "",
    "faire plaisir \"de quoi vous\"": "",
    "engager faciliter métier": "",
    "être v.i.p": "",
    "rien retenir": "",
    "petit prix grand vacance": "",
    "every matres need protection": "",
    "bien \"ça vous va\"": "",
    "mieux vivre vie": "",
    "rigolo apéritif": "",
    "grandir épanouir": "",
    "énergie mieux grandir": "",
    "parole \"à vous la\"": "",
    "chaîne information politique": "",
    "chaîne donne parole": "",
    "mieux choisir mieux acheter": "",
    "emballe monde": "",
    "inimitable 1857": "",
    "monde y gagne": "",
    "bien-être passion": "",
    "spirit of australia": "",
    "compagnie 5 étoile": "",
    "going place together": "",
    "instant beauté": "",
    "y quaker": "",
    "aimer vie": "",
    "your mountain": "",
    "lover what you eat": "",
    "faire équipe temps": "",
    "spirit of service": "",
    "mutuelle essentiel \"qui va à l'\"": "",
    "voix ici \"des gens d'\"": "",
    "cf. giovanni rana": "",
    "never hid": "",
    "genuine since 1937": "",
    "retrouver moyen": "",
    "banque conseil guider": "",
    "information gérer sécurité": "",
    "information gestion sécurité": "",
    "vivifier corps esprit": "",
    "boisson donne aiiile": "",
    "red bull donne aiiile": "",
    "the front page of the internet": "",
    "am what am": "",
    "vivre intensité": "",
    "bon réflexe bien loger": "",
    "reitman habill beauté": "",
    "parquet pronto subito bello sempr": "",
    "créateur automobile": "",
    "voiture vivre": "",
    "france avance renault accélèr": "",
    "changer vie changer automobile": "",
    "vie passion": "",
    "mieux renault entretenir renault": "",
    "santé beauté cheveu": "",
    "brûlure passer vie continue": "",
    "baisser coût rénovation": "",
    "vérand' attitude": "",
    "magazine enrichir vie": "",
    "bien manger plaisir partager": "",
    "rexoner laisser tomber": "",
    "radio or": "",
    "meilleur année 80": "",
    "meilleur hit": "",
    "meilleur musique": "",
    "pays gourmand": "",
    "petit coin nature": "",
    "ricard rien": "",
    "âge fatalité \"n'est pas une\"": "",
    "moving ideas forward": "",
    "imagine change": "",
    "bienfait nature": "",
    "ami petit-déjeuner": "",
    "rire rock": "",
    "rafraîchissement accent suisse": "",
    "info talk sport": "",
    "passer \"c'est là que ça se\"": "",
    "conduire roady": "",
    "mal dos affaire \"c'est notre\"": "",
    "promesse tenu": "",
    "vrai vie commencer intérieur": "",
    "haut protection peau sensible": "",
    "bien faire": "",
    "installer préserver excellence": "",
    "saveur automne": "",
    "créer durer": "",
    "beauty intelligence": "",
    "aile maroc": "",
    "encourager pause": "",
    "fuel your imagination": "",
    "radio musique \"ce n'est pas de la\" \"c'est de la\"": "",
    "pop rock": "",
    "accent divertissement": "",
    "bienvenue maison sain": "",
    "commerce \"c'est ça le\"": "",
    "radio 100 ardenne 100 hit": "",
    "couleur matière": "",
    "move your mind": "",
    "sabena y être déjà": "",
    "technologie action": "",
    "fort fondre fois": "",
    "ici commencer plaisir": "",
    "nature faire bien \"c'est dans sa\"": "",
    "saint-maclou habille maison": "",
    "inspirer vous": "",
    "vitalité vie \"c'est de la\"": "",
    "goût primeur": "",
    "bon lait brebis": "",
    "issu sport": "",
    "beauté commencer": "",
    "aime condo": "",
    "imagine the possibilities": "",
    "turn tomorrow": "",
    "monde inviter": "",
    "poursuivre passion": "",
    "store your world in ours": "",
    "garde peau sain": "",
    "essentiel santé \"c'est la\"": "",
    "expert gencive 1923": "",
    "value from idea": "",
    "bank for your idea": "",
    "for your numéro 1": "",
    "sanytol maison \"tout dans la\"": "",
    "numéro 1 chaussure internet": "",
    "the atlantic and you": "",
    "radin malin": "",
    "energy to the world": "",
    "bravo faire autant": "",
    "plein idée savourer": "",
    "fête manger ami \"c'est comme une\"": "",
    "saveur étonner": "",
    "simplement merveilleux": "",
    "idée grand distribution": "",
    "pied sentir bien": "",
    "qualité professionnel": "",
    "intelligent fahrzeuge": "",
    "we can explain": "",
    "entreprise familial": "",
    "voir entrée game": "",
    "brûler parfum homme": "",
    "faire main bas saleté": "",
    "you' re richer than you think": "",
    "mot \"chacun a son\"": "",
    "bien traverser manche": "",
    "we turn idea": "",
    "profiter journée": "",
    "auto emociòn": "",
    "technologie service plaisir": "",
    "technology to enjoy": "",
    "y' amour tasse \"a un peu d'\"": "",
    "loin \"être près de ceux qui sont\"": "",
    "sécurité vrai métier": "",
    "découverte produit original": "",
    "fort \"c'est plus\"": "",
    "the challenge will always be there": "",
    "personnalité montre": "",
    "recherche perfection": "",
    "fresh experience every time": "",
    "make the day work": "",
    "if it' s selley it works": "",
    "vivre bus": "",
    "the pursuit of perfect sound": "",
    "café sensationnel tasse": "",
    "avancer beauté": "",
    "cœur beauté": "",
    "chaîne série": "",
    " \"proche de tout\" \"proche de vous\"": "",
    "service eau": "",
    "facile \"et c'est\"": "",
    "abonné sfr simple numéro \"parce qu'un\" \"n'est pas qu'un\"": "",
    "monde fil \"est à vous\"": "",
    "parler mieux parler mobile": "",
    "vivre mobile": "",
    "monde vous.carrément": "",
    "accélérer \"et tout s'\"": "",
    "responsabilité création": "",
    "be sharp": "",
    " \"entre toi et moi\"": "",
    "made to move": "",
    "shell aime": "",
    "all for you": "",
    "maison côté zen": "",
    "spécialiste impeccable": "",
    "aller adorer rentrer": "",
    "équipe expert service nature": "",
    "mur mur": "",
    "your foot company": "",
    "être inspirer": "",
    "answers for industry": "",
    "extraordinaire voir quotidien": "",
    "amoureux sommeil \"pour tous les\"": "",
    "bien-être haut définition": "",
    "be happy be simply": "",
    "falloir \"juste ce qu'il vous\"": "",
    "prendre mobile main": "",
    "force roule": "",
    "relais frais": "",
    "souplesse instant": "",
    "boost yourself": "",
    "libre jouer libre salir": "",
    "skip offrir propreté \"plus que la\"": "",
    "simplement évident": "",
    "simply clever": "",
    "believe in better": "",
    " \"vous d'abord\"": "",
    "caring more about you": "",
    "start here": "",
    "pouvoir compter": "",
    "live smart": "",
    "gagne responsable \"tous à être\"": "",
    "moving people enhancing live": "",
    "train respire": "",
    "peine train déjà loin": "",
    "destination mieux": "",
    "donner train idée avance": "",
    "progrès valoir partager \"que s'il est\"": "",
    "faire préférer train \"à nous de vous\"": "",
    "idée avance": "",
    "satisfait pleinement": "",
    "mer plaisir \"pour que la\"": "",
    "eau saler jamais goût larme \"pour que l'\"": "",
    "ready to servir": "",
    "partenaire maîtrise risque": "",
    "souvenir goût": "",
    "liberté bon": "",
    "savourer vie": "",
    "faire jour jour meilleur": "",
    "service qualité vie": "",
    "my style my way": "",
    "esprit dressing": "",
    "avoir finir aimer chèvre": "",
    "soja avoir droit \"si c'est du\"": "",
    "expert investissement durable": "",
    "it' s so easy it' s somfy": "",
    "sens mouvement": "",
    "assurance auto résilier so malus assure": "",
    "we know how": "",
    "y doux maman \"ce qu'il\" \"a de plus\"": "",
    "réfléchissez signer": "",
    "meilleur chaussure": "",
    "allié vie artiste": "",
    "speedy \"va donc chez\"": "",
    "speedy entretenir confiance": "",
    "ambition partager": "",
    "absorber \"pas à peu près\"": "",
    "chaîne vouloir sport \"de ceux qui\"": "",
    "sport \"mais pas que\"": "",
    "gym esprit": "",
    "design your life": "",
    "meilleur forme meilleur vie": "",
    "ami net": "",
    "the now network": "",
    "faire mieux jour": "",
    "acheter bureau devenir facile": "",
    "that was easy": "",
    "monde réseau aérien": "",
    "logistique dernier kilomètre": "",
    "stella \"c'est près de ma\"": "",
    "beauté \"elle est de toute\"": "",
    "making good time": "",
    "nez respir": "",
    "numéro 1 mondial": "",
    "the innovators of comfort": "",
    "réussir avenir": "",
    "confiance évolution": "",
    "eat fresh": "",
    "préparer oeil": "",
    "manger frais": "",
    "chef \"c'est vous le\"": "",
    "défi excellence": "",
    "apporter essentiel vie": "",
    "expert lave vaissell": "",
    "sûr sun": "",
    "décider devenir facile": "",
    "swiffer passer poussière effacer": "",
    "always so good for so little": "",
    "naturellement au-dessus": "",
    "avancer assurer": "",
    "avenir commencer ici": "",
    "bien mal \"ça fait du\" \"là où ça fait\"": "",
    "think outsid the bun": "",
    "editeur mouvement": "",
    "équilibre ligne \"sur toute la\"": "",
    "esprit automobile": "",
    "totally sexy": "",
    "frais fort nature": "",
    "tanéo accompagne": "",
    "leadership with trust": "",
    "prix \"les plus bas\"": "",
    "aime prix": "",
    "very funny": "",
    "america' s most convenier bank": "",
    "professionnel direct": "",
    "pro \"tout pour les\"": "",
    "techni contact facilite achat professionnel": "",
    "protéger embellir": "",
    "passer \"comment s'en\"": "",
    "how easy": "",
    "continuer payer trop cher": "",
    "continuer téléphoner trop cher": "",
    "meilleur magazine télé": "",
    "da soll mal einer nachmachen": "",
    "envie programme": "",
    "futur simple": "",
    "partenaire nettoyage sol": "",
    "rien intellignet dent \"n'est plus\"": "",
    "nature voir": "",
    "every littl help": "",
    "tetra pak protéger bon \"ce qui est\"": "",
    "télévision émotion": "",
    "réponse textile": "",
    "basic is beautiful": "",
    "technology for innovator": "",
    "aimer aime \"la une vous\"": "",
    "prendre couleur \"sur la une\"": "",
    "mieux informer distraire y \"en a qu'une\" \"c'est la une\"": "",
    "tf1 cœur boom": "",
    "tf1 programme \"c'est tout un\"": "",
    "vie plein tf1": "",
    "mieux être tf1": "",
    "tf1 commun \"on a tous\"": "",
    "retrouve tf1": "",
    "partager onde positif": "",
    "télé très télé": "",
    "savoir télé": "",
    "cliquer scotcher \"et t'es\"": "",
    "être déjà suisse": "",
    "harmonie voyage": "",
    "renoncer rien \"pour ceux qui ne\"": "",
    "securising your futur": "",
    "train éclair": "",
    "ligne \"différent sur toute la\"": "",
    "énergie nature": "",
    "choix liberté": "",
    "surgelé gourmand": "",
    " \"n'importe où\" \"mais pas n'importe comment\"": "",
    "regarder écouter vivre": "",
    "image beyond": "",
    "technologie amie": "",
    "knowledge to act": "",
    "généreux nature": "",
    "voir kadéo": "",
    "concert sensation": "",
    "imaginer \"plus que vous n'\"": "",
    "amour 2 grand i.": "",
    "recette \"toute est dans la\"": "",
    "avoir jamais télé \"été aussi près de la\"": "",
    "bien sud \"mais c'est\"": "",
    "famille sud": "",
    "life is for sharing": "",
    "stick together": "",
    "intelligent accessorie": "",
    "voyager vouloir simplicité": "",
    "jouer tomy jamais finir": "",
    "bien trouver bien tomy": "",
    "passion manga portée clic": "",
    "trouver \"près de chez vous\"": "",
    "bon affaire attendre": "",
    "bien achat \"plus qu'un\"": "",
    "résistance certifier": "",
    "committed to people committed to the futur": "",
    "leading innovation": "",
    "your complete betting service": "",
    "changer habitude": "",
    "vouloir \"quand vous le\"": "",
    "today tomorrow toyota": "",
    "make things better": "",
    "promesse mieux faire": "",
    "moving forward": "",
    "mieux loin": "",
    "let' s go place": "",
    "au-delà performance": "",
    "jouet \"c'est nous\"": "",
    "amuser trop trop sérieux": "",
    "y bonheur r.": "",
    "efficacité métier": "",
    "the reliable choice": "",
    "premier télévision urbain": "",
    "in business to deliver": "",
    "envoyer argent simplement": "",
    "y temps \"a pas le\"": "",
    "livraison silence": "",
    "liberté avancer": "",
    "voir mike trattoria di": "",
    "évasion neige": "",
    "maîtrise dernier mètre": "",
    "sommeil coudre main": "",
    "network people trust": "",
    "télévision belge": "",
    "pluriel utile monde \"ouverte sur le\"": "",
    "programme chaîne échange \"comme la troisième\" \"ça ne s'\"": "",
    "code less create more": "",
    "journée commencer": "",
    "bel terre": "",
    "tryba vouloir \"n'est pas\"": "",
    "tuc rentrer bon moment \"c'est le\"": "",
    "vie émotion": "",
    "jouer vitesse supérieur": "",
    "monde monde": "",
    "ouvrir télé": "",
    "monde monde tv5monde": "",
    "chaîne culturel francophone mondial": "",
    "monde \"à vous le\"": "",
    "respirer télé \"c'est votre\"": "",
    "temps y penser": "",
    "truly bespok": "",
    "passer temps vendée": "",
    "t tea": "",
    "all is in the mix": "",
    "fois plaisir": "",
    "doigt coupe-faim": "",
    "pause twix sacrer": "",
    "retrouver état normal état normal \"quelque soit votre\"": "",
    "linux for human being": "",
    "grâce être \"je suis ce que je suis\" \"à ce que nous\"": "",
    "louer rester libre": "",
    "colle \"tout sur tout\"": "",
    "nutrition optimal": "",
    "succès \"c'est toujours un\"": "",
    "perfection coup": "",
    "bien chausser": "",
    "destination confiance": "",
    "the rechargeable specialist": "",
    "voir futur": "",
    "savoir surprendre": "",
    "être reconnaître": "",
    "amener loin": "",
    "faire santé \"toujours plus pour la\"": "",
    "concentré foot": "",
    "immobilier côté vie": "",
    "fly with us": "",
    "keeping kitchens cooking": "",
    "respecter peau nature \"c'est dans notre\"": "",
    "voyage aime": "",
    "brillant horizon": "",
    "voyage illimité": "",
    "voyage planète bleu": "",
    "v viande": "",
    "goût europe tasse": "",
    "tache évanouir": "",
    "varilu progress": "",
    "vedette mérite confiance": "",
    "faire changer idée l\"intérim \"on va vous\"": "",
    "douceur jambe mériter": "",
    "touche beauté": "",
    "getting you there in comfort": "",
    "environnement défi industriel": "",
    "boire vie vert": "",
    "commerçant bouger": "",
    "petit prix plein vie": "",
    "humain voyager": "",
    "we connect": "",
    "connecting you to the cloud": "",
    "architecte enfant": "",
    "santé passer peau \"aussi par la\"": "",
    "respirer vie": "",
    "roi pomme terre": "",
    "roi apéritif": "",
    "vie merde emmerde \"c'est de la\" \"et je vous\"": "",
    "climate of innovation": "",
    "fromage vrai": "",
    "y' fort \"a pas plus\"": "",
    "y mieux couper herbe": "",
    "ménagez vous vie": "",
    "vileda ménage vie": "",
    "vileda vie facile \"me rend la\"": "",
    "vif maison": "",
    "video sharing for you": "",
    "get more": "",
    "télé by virgin": "",
    "culture plaisir": "",
    "bien meilleur membre \"quand on est\"": "",
    "détendre mobile": "",
    "rock star music": "",
    "max tube": "",
    "impression \"plus qu'une\"": "",
    "faire impression": "",
    "exigeant nature": "",
    "revitteliser vous": "",
    "boire éliminez": "",
    "y chose eau": "",
    "créer changer vie \"ce qui vous\"": "",
    "chaîne chose \"qui a encore des\"": "",
    "chauffage électrique révolution": "",
    "solide cuisine vosge": "",
    "for life": "",
    "passion qualité": "",
    "understanding mobility": "",
    "voyage loin imaginer \"que vous ne l'\"": "",
    "télé évasion voyage voyageur": "",
    "télé point départ": "",
    "partir voir": "",
    "voir \"qui a vu\"": "",
    "aventure terre": "",
    "déjà donner autant plaisir \"qui vous a\"": "",
    "make it v good day": "",
    "everyone deserver quality food": "",
    "speak english wall street english": "",
    "micronutrition animal": "",
    "the power of yes": "",
    "bien ensemble \"on est si\"": "",
    "eau rare bienfaisant": "",
    "goût originel eau": "",
    "valeur pur": "",
    "garantie satisfait": "",
    "meilleur barbecue": "",
    "creativ protection": "",
    "naturel \"quoi de plus\"": "",
    "arrêter régime commencer weight watcher": "",
    "carrément bon": "",
    "quality is our recipe": "",
    "moving money for better": "",
    "envoyer argent mieux": "",
    "proprio y tenir \"parce que le\"": "",
    "lover where you' re going": "",
    "qualité vie \"c'est la\"": "",
    "sensing the difference": "",
    "cat know the difference": "",
    "chat savoir réclamer whiskas": "",
    "nourrir vrai nature": "",
    "deliciou fresh tasty all natural": "",
    "move you": "",
    "now you know": "",
    "knowledge for generation": "",
    "feel your skin": "",
    "ressourcez peau": "",
    "donner faim": "",
    "plaisir jour": "",
    "more win": "",
    "true mobile freedom": "",
    "nouveau approche vin": "",
    "fabuleux \"pour si peu\"": "",
    "réalisateur rêve": "",
    "go in the know": "",
    "powering world trade": "",
    "fixation professionnel": "",
    "play more": "",
    "jump in": "",
    "the document company": "",
    "the futur of awesome": "",
    "avion malin": "",
    "the next level": "",
    "bois adore": "",
    "amour bois": "",
    "y' mieux": "",
    "do you yahoo": "",
    "it' s you": "",
    "rev your heart": "",
    "freestyle mobile": "",
    "not for everyone": "",
    "fleur vie": "",
    "goûton vie bon côté": "",
    "more than sushi": "",
    "spiel dein leben laut": "",
    "music like": "",
    "broadcast yourself": "",
    "vie beauté": "",
    "professionnel immobilier": "",
    "jamais autant respecter nature femme \"on n'a\"": "",
    "réinventer jour": "",
    "immobilier métier": "",
    "monde merveilleux": "",
    "hurler plaisir": "",
    "free to be": "",
    "better tv better price": "",
    "bienvenue téléphonie libre": "",
    "télé 100 bouffe": "",
    "get more out of it": "",
    "uniting the world through languag": "",
    "tomorrow never waits": ""
}